MANIFEST.in
distribute_setup.py
setup.py
licenses/AAL.md
licenses/AFL-3.0.md
licenses/AGPL-3.0.md
licenses/APL-1.0.md
licenses/APSL-2.0.md
licenses/Apache-2.0.md
licenses/Artistic-2.0.md
licenses/BSD-2-Clause.md
licenses/BSD-3-Clause.md
licenses/BSL-1.0.md
licenses/CATOSL-1.1.md
licenses/CDDL-1.0.md
licenses/CECILL-2.1.md
licenses/CNRI-Python.md
licenses/CPAL-1.0.md
licenses/CUA-OPL-1.0.md
licenses/ECL-2.0.md
licenses/EFL-2.0.md
licenses/EPL-1.0.md
licenses/EUDatagrid.md
licenses/EUPL-1.1.md
licenses/Entessa.md
licenses/Fair.md
licenses/Frameworx-1.0.md
licenses/GPL-2.0.md
licenses/GPL-3.0.md
licenses/HPND.md
licenses/IPA.md
licenses/IPL-1.0.md
licenses/ISC.md
licenses/LGPL-2.1.md
licenses/LGPL-3.0.md
licenses/LPL-1.02.md
licenses/LPPL-1.3c.md
licenses/MIT.md
licenses/MPL-2.0.md
licenses/MS-PL.md
licenses/MS-RL.md
licenses/MirOS.md
licenses/Motosoto.md
licenses/Multics.md
licenses/NASA-1.3.md
licenses/NCSA.md
licenses/NGPL.md
licenses/NPOSL-3.0.md
licenses/NTP.md
licenses/Naumen.md
licenses/Nokia.md
licenses/OCLC-2.0.md
licenses/OFL-1.1.md
licenses/OGTSL.md
licenses/OSL-3.0.md
licenses/PHP-3.0.md
licenses/PostgreSQL.md
licenses/Python-2.0.md
licenses/QPL-1.0.md
licenses/RPL-1.5.md
licenses/RPSL-1.0.md
licenses/RSCPL.md
licenses/SPL-1.0.md
licenses/SimPL-2.0.md
licenses/Sleepycat.md
licenses/VSL-1.0.md
licenses/W3C.md
licenses/WXwindows.md
licenses/Watcom-1.0.md
licenses/Xnet.md
licenses/ZPL-2.0.md
licenses/Zlib.md
osi_licenses_full/__init__.py
osi_licenses_full.egg-info/PKG-INFO
osi_licenses_full.egg-info/SOURCES.txt
osi_licenses_full.egg-info/dependency_links.txt
osi_licenses_full.egg-info/entry_points.txt
osi_licenses_full.egg-info/not-zip-safe
osi_licenses_full.egg-info/requires.txt
osi_licenses_full.egg-info/top_level.txt