Metadata-Version: 1.0
Name: osi-licenses-full
Version: 0.1.0
Summary: A python utility for downloading all OSI approved licenses in markdown format
Home-page: https://github.com/liam-middlebrook/osi-licenses-full
Author: Liam Middlebrook
Author-email: liammiddlebrook@gmail.com
License: MIT
Keywords: osi foss markdown license
Platform: UNKNOWN
